[{"id":1,"name":"A1 Descrire l'apparance des gens","pos":10,"audio":false},{"id":2,"name":"A2 Parties du corps","pos":44,"audio":false},{"id":6,"name":"B1 Chez le médecin ( partie 1)","pos":101,"audio":false},{"id":7,"name":"B1 Chez le médecin ( partie 2)","pos":102,"audio":false},{"id":3,"name":"B1 Le visage","pos":83,"audio":false},{"id":5,"name":"B2 Habitudes et addictions","pos":129,"audio":false},{"id":9,"name":"B2 Maladies et affections","pos":131,"audio":false},{"id":4,"name":"B2 Organes internes","pos":128,"audio":false},{"id":8,"name":"B2 Traitements","pos":130,"audio":false}]