[{"id":1,"name":"Is  <b>anyone<\/b>  here?"},{"id":2,"name":"There is  <b>nobody<\/b>  here."},{"id":3,"name":"Did  <b>anybody<\/b>  see that?"},{"id":4,"name":"I know  <b>someone,<\/b>  who can help you."},{"id":5,"name":"There is  <b>somebody<\/b>  who wants to talk to you."},{"id":6,"name":"Do you have  <b>anything<\/b>  for me?"},{"id":7,"name":"I have  <b>nothing<\/b>  to add."},{"id":8,"name":"I have  <b>something<\/b>  for you."},{"id":9,"name":"<b>No one<\/b>  loves me!"},{"id":10,"name":"We should  <b>all<\/b>  go."}]