[{"id":1,"name":"Je suis là pour voir un médecin."},{"id":2,"name":"Es-tu malade?"},{"id":3,"name":"Je ne me sens pas très bien."},{"id":4,"name":"J'ai le nez qui coule et je tousse."},{"id":5,"name":"J'ai également un terrible mal de tête."},{"id":6,"name":"Je pense que j'ai attrapé un rhume."},{"id":7,"name":"C'est juste la grippe commune."},{"id":8,"name":"Quels médicaments recommandes-tu?"},{"id":9,"name":"Tu dois rester au lit et te reposer."},{"id":10,"name":"Peux-tu me faire un certificat médical?"}]