[{"id":1,"name":"Estás hablando demasiado <b> rápido <\/b>."},{"id":2,"name":"Come <b> despacio <\/b>."},{"id":3,"name":"Hazlo <b> rápido <\/b>."},{"id":4,"name":"Él se comportó <b> mal <\/b>."},{"id":5,"name":"Lo conozco <b> bien <\/b>."},{"id":6,"name":"¡Escucha <b> atentamente <\/b>!"},{"id":7,"name":"Mi padre trabaja muy <b> duro <\/b>."},{"id":8,"name":"Él ganó <b> fácilmente <\/b>."},{"id":9,"name":"Ella canta <b> terriblemente mal <\/b>."},{"id":10,"name":"Le pedí <b> amablemente <\/b> que se fuera."}]