[{"id":1,"name":"Puedes llegar en tren."},{"id":2,"name":"Me gustaría un billete a Madrid."},{"id":3,"name":"¿Solo ida o con vuelta?"},{"id":4,"name":"¿Puedo reservar un asiento con ventana en primera clase?"},{"id":5,"name":"¿En qué plataforma sale el tren a Londres?"},{"id":6,"name":"¿Dónde puedo encontrar el horario?"},{"id":7,"name":"Si no te das prisa, perderemos el tren."},{"id":8,"name":"¿Tenemos que cambiar de tren?"},{"id":9,"name":"El tren a París va con retraso."},{"id":10,"name":"¿Te importaría cambiar de asiento?"}]