[{"id":1,"name":"She checks her phone  <b>several<\/b>  times a day."},{"id":2,"name":"I met him a  <b>few<\/b>  days ago."},{"id":3,"name":"There were  <b>fewer<\/b>  people than expected."},{"id":4,"name":"There is a  <b>little<\/b>  time left."},{"id":5,"name":"They have  <b>less<\/b>  money than us."},{"id":6,"name":"She doesn't speak too <b> much<\/b> ."},{"id":7,"name":"<b>Many<\/b>  people have two cars."},{"id":8,"name":"<b>Many <\/b> of us are hungry."},{"id":9,"name":"They have  <b>more<\/b>  children than us."},{"id":10,"name":"<b>Most<\/b>  people don´t know me."}]