[{"id":1,"name":"Zawsze mnie do niej  <b>porównujesz<\/b>  ."},{"id":2,"name":"Ona <b> różni się od<\/b>  swojej siostry."},{"id":3,"name":"One są  <b>podobne<\/b> ."},{"id":4,"name":"Jesteś  <b>taka sama jak<\/b>  twoja matka."},{"id":5,"name":"Jest  <b>ładniejsza od<\/b>  niej."},{"id":6,"name":"On nie jest aż  <b>tak<\/b>  wysoki  <b>jak<\/b>  ty."},{"id":7,"name":"<b>Przypominasz<\/b>  mi kogoś."},{"id":8,"name":"Mamy ze sobą  <b>wiele wspólnego<\/b> ."},{"id":9,"name":"<b>Oboje<\/b>  lubimy robić zakupy."},{"id":10,"name":"<b>Żaden z nas<\/b>  nie potrafi prowadzić samochodu."}]