[{"id":1,"name":"Il est <b> dans <\/b> ma chambre."},{"id":2,"name":"Le livre est <b> sur <\/b> ton bureau."},{"id":3,"name":"Il y a un chien <b> en dessous <\/b> du lit."},{"id":4,"name":"L'avion vole <b> au-dessus <\/b> de la ville."},{"id":5,"name":"Il y a quelqu'un <b> derrièr <\/b> e toi."},{"id":6,"name":"Il est assis <b> en face de <\/b> moi."},{"id":7,"name":"Le magasin se trouve <b> entre <\/b> la banque et l'église."},{"id":8,"name":"Le bureau de poste est <b> juste au coin <\/b>."},{"id":9,"name":"Mon bureau se trouve <b> près de <\/b> l'arrêt de bus."},{"id":10,"name":"J'ai marché <b> à travers <\/b> ces montagnes."}]