[{"id":1,"name":"<b> Le printemps <\/b>  est ma saison préférée."},{"id":2,"name":"<b> L'été <\/b>  en Egypte est vraiment très chaud."},{"id":3,"name":"Il pleut souvent ici en  <b> automne <\/b> ."},{"id":4,"name":"Est-ce qu'il neige ici en <b>  hiver <\/b>  ?"},{"id":5,"name":"Le temps hier était <b>  épouvantable <\/b> ."},{"id":6,"name":"Quelles sont les <b>  prévisions météorologiques <\/b>  pour demain ?"},{"id":7,"name":"Le temps sera  <b> nuageu <\/b> x la plupart de la journée."},{"id":8,"name":"Il va  <b> pleuvoir <\/b> ."},{"id":9,"name":"Nous nous attendons à un  <b> orage <\/b> ."},{"id":10,"name":"La <b>  température  <\/b> peut chuter en dessous de zéro."}]