[{"id":1,"name":"Naszym obowiązkiem jest chronić <b>przyrodę<\/b>."},{"id":2,"name":"Ludzie generują dużo<b> śmieci.<\/b>"},{"id":3,"name":"Dlatego <b>recykling<\/b> jest ważny dla środowiska."},{"id":4,"name":"Tygrysy są<b> gatunkiem zagrożonym<\/b>."},{"id":5,"name":"Powietrze w naszym mieście jest bardzo <b>zanieczyszczone<\/b>."},{"id":6,"name":"Nad Nowym Jorkiem unosi się<b> smog<\/b>."},{"id":7,"name":"<b>Globalne ocieplenie<\/b> może mieć poważne konsekwencje."},{"id":8,"name":"<b>Żywność ekologiczna<\/b> stała się bardzo popularna."},{"id":9,"name":"Samochody elektryczne są <b>przyjazne dla środowiska<\/b>."},{"id":10,"name":"Wiatr jest źródłem<b> energii odnawialnej<\/b>."}]